topsis_abhishek/__init__.py
Topsis_Abhishek_Verma_102203309-0.1.dist-info/LICENSE.txt
Topsis_Abhishek_Verma_102203309-0.1.dist-info/METADATA
Topsis_Abhishek_Verma_102203309-0.1.dist-info/WHEEL
Topsis_Abhishek_Verma_102203309-0.1.dist-info/top_level.txt
Topsis_Abhishek_Verma_102203309-0.1.dist-info/RECORD
