Metadata-Version: 2.2
Name: Topsis-Abhishek-Verma-102203309
Version: 0.1
Summary: Package For Topsis
Author: <Abhishek Verma
Author-email: mv3020740@gmail.com
Classifier: Programming Language :: Python :: 3
Classifier: License :: OSI Approved :: MIT License
Classifier: Operating System :: OS Independent
License-File: LICENSE.txt
Dynamic: author
Dynamic: author-email
Dynamic: classifier
Dynamic: summary
